startpage.py
startpage_parser-1.0.0.dist-info/LICENSE
startpage_parser-1.0.0.dist-info/METADATA
startpage_parser-1.0.0.dist-info/WHEEL
startpage_parser-1.0.0.dist-info/top_level.txt
startpage_parser-1.0.0.dist-info/RECORD
