Metadata-Version: 2.1
Name: startpage-parser
Version: 1.0.0
Summary: parsing search results from startpage search engine (based on google.com results)
Home-page: https://github.com/knassar702/startpage-parser
License: GPL-3.0 License
Platform: UNKNOWN
Requires-Python: >=3.6
Requires-Dist: bs4
Requires-Dist: requests
